biomaj_data/__init__.py
biomaj_data/utils.py
biomaj_data/db_properties/Anopheles_gambiae.properties
biomaj_data/db_properties/Arabidopsis_thaliana.properties
biomaj_data/db_properties/Bos_taurus.properties
biomaj_data/db_properties/Drosophila_ananassae-flybase.properties
biomaj_data/db_properties/Drosophila_erecta-flybase.properties
biomaj_data/db_properties/Drosophila_grimshawi-flybase.properties
biomaj_data/db_properties/Drosophila_melanogaster-flybase.properties
biomaj_data/db_properties/Drosophila_melanogaster.properties
biomaj_data/db_properties/Drosophila_mojavensis-flybase.properties
biomaj_data/db_properties/Drosophila_persimilis-flybase.properties
biomaj_data/db_properties/Drosophila_pseudoobscura-flybase.properties
biomaj_data/db_properties/Drosophila_sechellia-flybase.properties
biomaj_data/db_properties/Drosophila_simulans-flybase.properties
biomaj_data/db_properties/Drosophila_virilis-flybase.properties
biomaj_data/db_properties/Drosophila_willistoni-flybase.properties
biomaj_data/db_properties/Drosophila_yakuba-flybase.properties
biomaj_data/db_properties/Ensembl_plants.properties
biomaj_data/db_properties/Homo_sapiens-hg38-ucsc.properties
biomaj_data/db_properties/Monodelphis_domestica.properties
biomaj_data/db_properties/Mus_musculus-ncbi.properties
biomaj_data/db_properties/NR.properties
biomaj_data/db_properties/PFam.properties
biomaj_data/db_properties/SILVA.properties
biomaj_data/db_properties/UniProt.properties
biomaj_data/db_properties/alu.properties
biomaj_data/db_properties/alu_iput_irods.properties
biomaj_data/db_properties/frogs.properties
biomaj_data/db_properties/genbank.properties
biomaj_data/db_properties/human_genomic.properties
biomaj_data/db_properties/refseq.properties
biomaj_data/db_properties/swissprot.properties
biomaj_data-3.1.3.dist-info/METADATA
biomaj_data-3.1.3.dist-info/WHEEL
biomaj_data-3.1.3.dist-info/top_level.txt
biomaj_data-3.1.3.dist-info/RECORD
